plato_msap4_demonstrator/__init__.py
plato_msap4_demonstrator/aux.py
plato_msap4_demonstrator/background.py
plato_msap4_demonstrator/correlation.py
plato_msap4_demonstrator/fliper.py
plato_msap4_demonstrator/lomb_scargle.py
plato_msap4_demonstrator/morphology.py
plato_msap4_demonstrator/output.py
plato_msap4_demonstrator/rooster.py
plato_msap4_demonstrator/rotation_pipeline.py
plato_msap4_demonstrator/wavelets.py
plato_msap4_demonstrator/catalogs/__init__.py
plato_msap4_demonstrator/catalogs/plato-sim.csv
plato_msap4_demonstrator/catalogs/santos-19-21.csv
plato_msap4_demonstrator/catalogs/santos-21-norot.csv
plato_msap4_demonstrator/catalogs/santos_2019_catalog.fit
plato_msap4_demonstrator/catalogs/santos_2021_catalog.fit
plato_msap4_demonstrator/catalogs/santos_2021_norot.fit
plato_msap4_demonstrator/constants/__init__.py
plato_msap4_demonstrator/constants/constants.hdf5
plato_msap4_demonstrator/rooster_instances/__init__.py
plato_msap4_demonstrator/timeseries/003733735.fits
plato_msap4_demonstrator/timeseries/__init__.py
plato_msap4_demonstrator/timeseries/epic211015853.fits
plato_msap4_demonstrator/timeseries/kic003733735_longcadence_kepseismic.fits
plato_msap4_demonstrator-0.2.1.dist-info/LICENSE
plato_msap4_demonstrator-0.2.1.dist-info/METADATA
plato_msap4_demonstrator-0.2.1.dist-info/WHEEL
plato_msap4_demonstrator-0.2.1.dist-info/top_level.txt
plato_msap4_demonstrator-0.2.1.dist-info/RECORD
