Metadata-Version: 2.1
Name: plato_msap4_demonstrator
Version: 0.2.1
Summary: PLATO MSAP4 demonstrator for stellar surface rotation and activity analysis
Author-email: "Sylvain N. Breton" <sylvain.breton@inaf.it>
License: 
Project-URL: Homepage, https://gitlab.com/sybreton/plato_rotation_pipeline
Project-URL: Documentation, https://plato-rotation-pipeline.readthedocs.io/en/latest/
Keywords: stellar physics,stellar rotation,stellar activity,solar-type stars,PLATO
Classifier: Programming Language :: Python :: 3
Classifier: License :: OSI Approved :: CEA CNRS Inria Logiciel Libre License, version 2.1 (CeCILL-2.1)
Classifier: Operating System :: OS Independent
Requires-Python: >=3.7
License-File: LICENSE
Requires-Dist: numpy
Requires-Dist: pandas
Requires-Dist: matplotlib
Requires-Dist: astropy
Requires-Dist: scipy
Requires-Dist: numba
Requires-Dist: tqdm
Requires-Dist: emcee
Requires-Dist: corner
Requires-Dist: apollinaire
Requires-Dist: scikit-learn
Requires-Dist: scikit-image
Requires-Dist: ssqueezepy
